[
    {
        "block_height": "68",
        "block_id": "block_0",
        "block_left": "1186",
        "block_top": "118",
        "block_width": "1356",
        "file_path": "mdf-44_JHN-1901/mdf-44_JHN-1901-027_2R.xml",
        "height": "68",
        "left": "1186",
        "max_height": "4504",
        "max_width": "3001",
        "text": "Кемгафтувъце Пак. 47",
        "text_pred": "Кемгафтувъце Пакш. 4",
        "top": "118",
        "unit": "pixel",
        "width": "1356"
    },
    {
        "block_height": "432",
        "block_id": "block_1",
        "block_left": "359",
        "block_top": "299",
        "block_width": "2262",
        "file_path": "mdf-44_JHN-1901/mdf-44_JHN-1901-027_2R.xml",
        "height": "92",
        "left": "572",
        "max_height": "4504",
        "max_width": "3001",
        "text": "16. Тонафиензън тяеньди первай исьть шарь-",
        "text_pred": "16. Тонафніензън тԙньди первай исьть шарь",
        "top": "299",
        "unit": "pixel",
        "width": "2041"
    },
    {
        "block_height": "432",
        "block_id": "block_1",
        "block_left": "359",
        "block_top": "299",
        "block_width": "2262",
        "file_path": "mdf-44_JHN-1901/mdf-44_JHN-1901-027_2R.xml",
        "height": "92",
        "left": "363",
        "max_height": "4504",
        "max_width": "3001",
        "text": "къдюфт; а менелень славас Гисузть тумдънза меляе",
        "text_pred": "къдофт; а менелень славас Іисузть тумдънза мелԙ",
        "top": "419",
        "unit": "pixel",
        "width": "2255"
    },
    {
        "block_height": "432",
        "block_id": "block_1",
        "block_left": "359",
        "block_top": "299",
        "block_width": "2262",
        "file_path": "mdf-44_JHN-1901/mdf-44_JHN-1901-027_2R.xml",
        "height": "91",
        "left": "359",
        "max_height": "4504",
        "max_width": "3001",
        "text": "ляедьсь мяелезъст Валда-Сёрмать стама азфъпц, сякада",
        "text_pred": "лԙдьсь мԙлезъст Валда-Сёрмать стама азфъц, сякада",
        "top": "540",
        "unit": "pixel",
        "width": "2262"
    },
    {
        "block_height": "432",
        "block_id": "block_1",
        "block_left": "359",
        "block_top": "299",
        "block_width": "2262",
        "file_path": "mdf-44_JHN-1901/mdf-44_JHN-1901-027_2R.xml",
        "height": "73",
        "left": "361",
        "max_height": "4504",
        "max_width": "3001",
        "text": "станяе т1езьгяе Теенза.",
        "text_pred": "станԙ тіезьгԙ Теенза.",
        "top": "658",
        "unit": "pixel",
        "width": "910"
    },
    {
        "block_height": "327",
        "block_id": "block_2",
        "block_left": "361",
        "block_top": "780",
        "block_width": "2262",
        "file_path": "mdf-44_JHN-1901/mdf-44_JHN-1901-027_2R.xml",
        "height": "92",
        "left": "579",
        "max_height": "4504",
        "max_width": "3001",
        "text": "17. Садынгеляе мартънза уленьди народсь азън-",
        "text_pred": "17. Сядынгелԙ мартънза уленьди народсь азън-",
        "top": "780",
        "unit": "pixel",
        "width": "2040"
    },
    {
        "block_height": "327",
        "block_id": "block_2",
        "block_left": "361",
        "block_top": "780",
        "block_width": "2262",
        "file_path": "mdf-44_JHN-1901/mdf-44_JHN-1901-027_2R.xml",
        "height": "93",
        "left": "361",
        "max_height": "4504",
        "max_width": "3001",
        "text": "дъзяе Сонь Лазарьть калмъста лихьтеманц кулъстънга",
        "text_pred": "дъзԙ Сонь Лазарьть калмъста лихьтеманц кулъстънга",
        "top": "902",
        "unit": "pixel",
        "width": "2262"
    },
    {
        "block_height": "327",
        "block_id": "block_2",
        "block_left": "361",
        "block_top": "780",
        "block_width": "2262",
        "file_path": "mdf-44_JHN-1901/mdf-44_JHN-1901-027_2R.xml",
        "height": "79",
        "left": "363",
        "max_height": "4504",
        "max_width": "3001",
        "text": "ЖИВ'ЪЛлГЪДЪМанц.",
        "text_pred": "живългъдъміанц.",
        "top": "1028",
        "unit": "pixel",
        "width": "628"
    },
    {
        "block_height": "211",
        "block_id": "block_3",
        "block_left": "363",
        "block_top": "1141",
        "block_width": "2258",
        "file_path": "mdf-44_JHN-1901/mdf-44_JHN-1901-027_2R.xml",
        "height": "92",
        "left": "579",
        "max_height": "4504",
        "max_width": "3001",
        "text": "18. Тяе оцю-тевънц ланга марямань кувалма на-",
        "text_pred": "18. Тԙ оцю-тевънц ланга марямань кувалма на-",
        "top": "1141",
        "unit": "pixel",
        "width": "2042"
    },
    {
        "block_height": "211",
        "block_id": "block_3",
        "block_left": "363",
        "block_top": "1141",
        "block_width": "2258",
        "file_path": "mdf-44_JHN-1901/mdf-44_JHN-1901-027_2R.xml",
        "height": "69",
        "left": "363",
        "max_height": "4504",
        "max_width": "3001",
        "text": "родськяе лисьсь каршъзънза.",
        "text_pred": "родськԙ лисьсь каршъзънза.",
        "top": "1283",
        "unit": "pixel",
        "width": "1151"
    },
    {
        "block_height": "329",
        "block_id": "block_4",
        "block_left": "366",
        "block_top": "1383",
        "block_width": "2262",
        "file_path": "mdf-44_JHN-1901/mdf-44_JHN-1901-027_2R.xml",
        "height": "88",
        "left": "579",
        "max_height": "4504",
        "max_width": "3001",
        "text": "19. А Фарисейхьняе эсь ёткуваст кортасьть: ва",
        "text_pred": "19. А Фарисейхьнԙ эсь ёткуваст кортасьть: ва",
        "top": "1383",
        "unit": "pixel",
        "width": "2049"
    },
    {
        "block_height": "329",
        "block_id": "block_4",
        "block_left": "366",
        "block_top": "1383",
        "block_width": "2262",
        "file_path": "mdf-44_JHN-1901/mdf-44_JHN-1901-027_2R.xml",
        "height": "90",
        "left": "366",
        "max_height": "4504",
        "max_width": "3001",
        "text": "вяРйсасьть-Ъли тяени эЭсь аф кенереманьнтень  мезя-",
        "text_pred": "нԙйсасьть-ъли тԙни эсь аф кенереманьнтень мезя-",
        "top": "1502",
        "unit": "pixel",
        "width": "2262"
    },
    {
        "block_height": "329",
        "block_id": "block_4",
        "block_left": "366",
        "block_top": "1383",
        "block_width": "2262",
        "file_path": "mdf-44_JHN-1901/mdf-44_JHN-1901-027_2R.xml",
        "height": "91",
        "left": "367",
        "max_height": "4504",
        "max_width": "3001",
        "text": "мъска? сембяе мастърсь видеми мельганза.",
        "text_pred": "мъска сембԙ мастърсь видеми мельганза.",
        "top": "1621",
        "unit": "pixel",
        "width": "1743"
    },
    {
        "block_height": "212",
        "block_id": "block_5",
        "block_left": "366",
        "block_top": "1741",
        "block_width": "2262",
        "file_path": "mdf-44_JHN-1901/mdf-44_JHN-1901-027_2R.xml",
        "height": "91",
        "left": "578",
        "max_height": "4504",
        "max_width": "3001",
        "text": "20. Празьнекьти сафнень ёткса улельть Грект",
        "text_pred": "20. разьнекьти сафнень ёткса улельть Грек",
        "top": "1741",
        "unit": "pixel",
        "width": "2050"
    },
    {
        "block_height": "212",
        "block_id": "block_5",
        "block_left": "366",
        "block_top": "1741",
        "block_width": "2262",
        "file_path": "mdf-44_JHN-1901/mdf-44_JHN-1901-027_2R.xml",
        "height": "69",
        "left": "366",
        "max_height": "4504",
        "max_width": "3001",
        "text": "кати-мзярънест.",
        "text_pred": "кати-мзярънест.",
        "top": "1884",
        "unit": "pixel",
        "width": "622"
    },
    {
        "block_height": "335",
        "block_id": "block_6",
        "block_left": "370",
        "block_top": "1982",
        "block_width": "2261",
        "file_path": "mdf-44_JHN-1901/mdf-44_JHN-1901-027_2R.xml",
        "height": "87",
        "left": "578",
        "max_height": "4504",
        "max_width": "3001",
        "text": "21. Синь нежедьсьть Филипти, Галилея мастърЪвь",
        "text_pred": "21. Синь нежедьсьть Филипти, Галилея мастърънь",
        "top": "1982",
        "unit": "pixel",
        "width": "2052"
    },
    {
        "block_height": "335",
        "block_id": "block_6",
        "block_left": "370",
        "block_top": "1982",
        "block_width": "2261",
        "file_path": "mdf-44_JHN-1901/mdf-44_JHN-1901-027_2R.xml",
        "height": "88",
        "left": "370",
        "max_height": "4504",
        "max_width": "3001",
        "text": "Виесаидэряейти, эняельдсьть теенза кортазь: Минь м2е-",
        "text_pred": "Виѳсаидэрԙйти, энԙльдсьть теенза кортазь: минь мԙ-",
        "top": "2107",
        "unit": "pixel",
        "width": "2261"
    },
    {
        "block_height": "335",
        "block_id": "block_6",
        "block_left": "370",
        "block_top": "1982",
        "block_width": "2261",
        "file_path": "mdf-44_JHN-1901/mdf-44_JHN-1901-027_2R.xml",
        "height": "95",
        "left": "370",
        "max_height": "4504",
        "max_width": "3001",
        "text": "ленькяе Тисузть нявемс.",
        "text_pred": "ленькԙ Іисузть нԙемс.",
        "top": "2222",
        "unit": "pixel",
        "width": "937"
    },
    {
        "block_height": "211",
        "block_id": "block_7",
        "block_left": "371",
        "block_top": "2345",
        "block_width": "2264",
        "file_path": "mdf-44_JHN-1901/mdf-44_JHN-1901-027_2R.xml",
        "height": "86",
        "left": "580",
        "max_height": "4504",
        "max_width": "3001",
        "text": "22. Филипсь моли тяень азъма Андрейти; тоса",
        "text_pred": "22. Филипсь моли тԙнь азъма Андрейти; тоса",
        "top": "2345",
        "unit": "pixel",
        "width": "2055"
    },
    {
        "block_height": "211",
        "block_id": "block_7",
        "block_left": "371",
        "block_top": "2345",
        "block_width": "2264",
        "file_path": "mdf-44_JHN-1901/mdf-44_JHN-1901-027_2R.xml",
        "height": "95",
        "left": "371",
        "max_height": "4504",
        "max_width": "3001",
        "text": "Андрейть марта Филипсь азсазь Гисузти.",
        "text_pred": "Андрейть марта Филипсь азсазь Іисузти.",
        "top": "2461",
        "unit": "pixel",
        "width": "1668"
    },
    {
        "block_height": "211",
        "block_id": "block_8",
        "block_left": "373",
        "block_top": "2582",
        "block_width": "2260",
        "file_path": "mdf-44_JHN-1901/mdf-44_JHN-1901-027_2R.xml",
        "height": "96",
        "left": "581",
        "max_height": "4504",
        "max_width": "3001",
        "text": "23. Теест Гисузсь пшкяедьсь: сась Ломанень Цё-",
        "text_pred": "23. Теест Іисузсь пшкԙдьсь: сась Ломанень Цё-",
        "top": "2582",
        "unit": "pixel",
        "width": "2052"
    },
    {
        "block_height": "211",
        "block_id": "block_8",
        "block_left": "373",
        "block_top": "2582",
        "block_width": "2260",
        "file_path": "mdf-44_JHN-1901/mdf-44_JHN-1901-027_2R.xml",
        "height": "67",
        "left": "373",
        "max_height": "4504",
        "max_width": "3001",
        "text": "рать менель-славанц пингъц.",
        "text_pred": "рать менель-славанц пингъц.",
        "top": "2726",
        "unit": "pixel",
        "width": "1176"
    },
    {
        "block_height": "331",
        "block_id": "block_9",
        "block_left": "373",
        "block_top": "2826",
        "block_width": "2264",
        "file_path": "mdf-44_JHN-1901/mdf-44_JHN-1901-027_2R.xml",
        "height": "90",
        "left": "585",
        "max_height": "4504",
        "max_width": "3001",
        "text": "24. Видеста, видеста кортан тееньнть: тозер-",
        "text_pred": "24. Видеста. видеста кортан тееньнть: тозер-",
        "top": "2826",
        "unit": "pixel",
        "width": "2048"
    },
    {
        "block_height": "331",
        "block_id": "block_9",
        "block_left": "373",
        "block_top": "2826",
        "block_width": "2264",
        "file_path": "mdf-44_JHN-1901/mdf-44_JHN-1901-027_2R.xml",
        "height": "90",
        "left": "373",
        "max_height": "4504",
        "max_width": "3001",
        "text": "зёрнанзяесь станяк иляды ськамнянза, кулъфтяерей сон",
        "text_pred": "зёрнанԙсь станяк иляды ськамнянза, кулъфтԙрԙй сон",
        "top": "2947",
        "unit": "pixel",
        "width": "2264"
    },
    {
        "block_height": "331",
        "block_id": "block_9",
        "block_left": "373",
        "block_top": "2826",
        "block_width": "2264",
        "file_path": "mdf-44_JHN-1901/mdf-44_JHN-1901-027_2R.xml",
        "height": "90",
        "left": "375",
        "max_height": "4504",
        "max_width": "3001",
        "text": "модас прамстънза; а кулъвьдяеряей, лама кенерьфь ванды.",
        "text_pred": "модас прамстънза; а кулъньдԙрԙй, лама кенерьфь канды.",
        "top": "3067",
        "unit": "pixel",
        "width": "2259"
    },
    {
        "block_height": "331",
        "block_id": "block_10",
        "block_left": "378",
        "block_top": "3185",
        "block_width": "2262",
        "file_path": "mdf-44_JHN-1901/mdf-44_JHN-1901-027_2R.xml",
        "height": "92",
        "left": "589",
        "max_height": "4504",
        "max_width": "3001",
        "text": "25. Кельгись эсь ваймънц, юмафцы сон; аф",
        "text_pred": "25. Кельгись эсь ваймънц, юмафцы сон; аф",
        "top": "3185",
        "unit": "pixel",
        "width": "2049"
    },
    {
        "block_height": "331",
        "block_id": "block_10",
        "block_left": "378",
        "block_top": "3185",
        "block_width": "2262",
        "file_path": "mdf-44_JHN-1901/mdf-44_JHN-1901-027_2R.xml",
        "height": "91",
        "left": "378",
        "max_height": "4504",
        "max_width": "3001",
        "text": "кельгись эсь ваймЪнц тяе эрямстънза ванфтсы сонь",
        "text_pred": "кельгись эсь ваймънц тԙ эрямстънза ванфтсы сонь",
        "top": "3307",
        "unit": "pixel",
        "width": "2262"
    },
    {
        "block_height": "331",
        "block_id": "block_10",
        "block_left": "378",
        "block_top": "3185",
        "block_width": "2262",
        "file_path": "mdf-44_JHN-1901/mdf-44_JHN-1901-027_2R.xml",
        "height": "68",
        "left": "378",
        "max_height": "4504",
        "max_width": "3001",
        "text": "пингень-пивгеънь эрямати.",
        "text_pred": "пингень-шингсънь эрямати.",
        "top": "3448",
        "unit": "pixel",
        "width": "1080"
    },
    {
        "block_height": "335",
        "block_id": "block_11",
        "block_left": "380",
        "block_top": "3544",
        "block_width": "2262",
        "file_path": "mdf-44_JHN-1901/mdf-44_JHN-1901-027_2R.xml",
        "height": "93",
        "left": "592",
        "max_height": "4504",
        "max_width": "3001",
        "text": "26. Уряезя2 Мовь мельган молезавък: коса у-",
        "text_pred": "26. Урԙзԙ Монь мельган молезавък: коса у-",
        "top": "3544",
        "unit": "pixel",
        "width": "2046"
    },
    {
        "block_height": "335",
        "block_id": "block_11",
        "block_left": "380",
        "block_top": "3544",
        "block_width": "2262",
        "file_path": "mdf-44_JHN-1901/mdf-44_JHN-1901-027_2R.xml",
        "height": "91",
        "left": "380",
        "max_height": "4504",
        "max_width": "3001",
        "text": "лян Мон, эзк ули  урзезевък. — Моньдень . служама",
        "text_pred": "лян Мон, эзк ули урԙзевък. Моньдень служама",
        "top": "3667",
        "unit": "pixel",
        "width": "2262"
    },
    {
        "block_height": "335",
        "block_id": "block_11",
        "block_left": "380",
        "block_top": "3544",
        "block_width": "2262",
        "file_path": "mdf-44_JHN-1901/mdf-44_JHN-1901-027_2R.xml",
        "height": "91",
        "left": "380",
        "max_height": "4504",
        "max_width": "3001",
        "text": "кармайть лувсы Монь Аляезя.",
        "text_pred": "кармайть лувсы Монь Алԙзԙ.",
        "top": "3788",
        "unit": "pixel",
        "width": "1236"
    },
    {
        "block_height": "313",
        "block_id": "block_12",
        "block_left": "384",
        "block_top": "3908",
        "block_width": "2258",
        "file_path": "mdf-44_JHN-1901/mdf-44_JHN-1901-027_2R.xml",
        "height": "85",
        "left": "592",
        "max_height": "4504",
        "max_width": "3001",
        "text": "27. Тлени кавьзедезюсь ваймезяе; мезяма азан",
        "text_pred": "27. Тԙни каньзедезюсь ваймезԙ; мезяма азан",
        "top": "3908",
        "unit": "pixel",
        "width": "2050"
    },
    {
        "block_height": "313",
        "block_id": "block_12",
        "block_left": "384",
        "block_top": "3908",
        "block_width": "2258",
        "file_path": "mdf-44_JHN-1901/mdf-44_JHN-1901-027_2R.xml",
        "height": "93",
        "left": "386",
        "max_height": "4504",
        "max_width": "3001",
        "text": "Мон? Алей! ванфтъмак сле частстън! Да Мон саньгяе",
        "text_pred": "Мон? Алԙй! ванфтъмак сԙ частстън (а Мон саньгԙ",
        "top": "4023",
        "unit": "pixel",
        "width": "2253"
    },
    {
        "block_height": "313",
        "block_id": "block_12",
        "block_left": "384",
        "block_top": "3908",
        "block_width": "2258",
        "file_path": "mdf-44_JHN-1901/mdf-44_JHN-1901-027_2R.xml",
        "height": "50",
        "left": "384",
        "max_height": "4504",
        "max_width": "3001",
        "text": "тяе частти.",
        "text_pred": "тԙ частти.",
        "top": "4171",
        "unit": "pixel",
        "width": "431"
    }
]